f3ts_hardware_utils/__init__.py
f3ts_hardware_utils/ad3/WF_SDK/__init__.py
f3ts_hardware_utils/ad3/WF_SDK/device.py
f3ts_hardware_utils/ad3/WF_SDK/dmm.py
f3ts_hardware_utils/ad3/WF_SDK/logic.py
f3ts_hardware_utils/ad3/WF_SDK/pattern.py
f3ts_hardware_utils/ad3/WF_SDK/protocol/__init__.py
f3ts_hardware_utils/ad3/WF_SDK/protocol/i2c.py
f3ts_hardware_utils/ad3/WF_SDK/protocol/spi.py
f3ts_hardware_utils/ad3/WF_SDK/protocol/uart.py
f3ts_hardware_utils/ad3/WF_SDK/scope.py
f3ts_hardware_utils/ad3/WF_SDK/static.py
f3ts_hardware_utils/ad3/WF_SDK/supplies.py
f3ts_hardware_utils/ad3/WF_SDK/tools.py
f3ts_hardware_utils/ad3/WF_SDK/wavegen.py
f3ts_hardware_utils/ad3/__init__.py
f3ts_hardware_utils/ad3/ad3.py
f3ts_hardware_utils/aimtti.py
f3ts_hardware_utils/cisco/__init__.py
f3ts_hardware_utils/cisco/api.py
f3ts_hardware_utils/cisco/api_client.py
f3ts_hardware_utils/cisco/serial_interface.py
f3ts_hardware_utils/color_sensors.py
f3ts_hardware_utils/dp100/README.md
f3ts_hardware_utils/dp100/__init__.py
f3ts_hardware_utils/dp100/dp100_interface.py
f3ts_hardware_utils/dp100/installation/99-atk-dp100.rules
f3ts_hardware_utils/dp100/installation/hidapi-win/x64/hidapi.dll
f3ts_hardware_utils/dp100/installation/hidapi-win/x64/hidapi.lib
f3ts_hardware_utils/dp100/installation/hidapi-win/x64/hidapi.pdb
f3ts_hardware_utils/dp100/installation/hidapi-win/x86/hidapi.dll
f3ts_hardware_utils/dp100/installation/hidapi-win/x86/hidapi.lib
f3ts_hardware_utils/dp100/installation/hidapi-win/x86/hidapi.pdb
f3ts_hardware_utils/dp100/tests/test_discovery_auto.py
f3ts_hardware_utils/dp100/tests/test_poweron.py
f3ts_hardware_utils/feasa.py
f3ts_hardware_utils/ffc/__init__.py
f3ts_hardware_utils/ffc/api.py
f3ts_hardware_utils/ffc/api_client.py
f3ts_hardware_utils/ffc/serial_interface.py
f3ts_hardware_utils/ffc/tests/test_discovery.py
f3ts_hardware_utils/ffio/__init__.py
f3ts_hardware_utils/ffio/serial_interface.py
f3ts_hardware_utils/ffio/tests/test_discovery.py
f3ts_hardware_utils/ffio/tests/test_gpio.py
f3ts_hardware_utils-0.1.26.dist-info/METADATA
f3ts_hardware_utils-0.1.26.dist-info/WHEEL
f3ts_hardware_utils-0.1.26.dist-info/entry_points.txt
f3ts_hardware_utils-0.1.26.dist-info/licenses/LICENSE
f3ts_hardware_utils-0.1.26.dist-info/RECORD
