Metadata-Version: 2.4
Name: f3ts-hardware-utils
Version: 0.1.26
Summary: FixturFab Functional Test System Hardware Utilities Library. Connect and control test hardware for your FixturFab Functional Test System.
License-File: LICENSE
Author: Duncan Lowder
Author-email: duncan@fixturfab.com
Requires-Python: >=3.10,<4.0
Classifier: Programming Language :: Python :: 3
Classifier: Programming Language :: Python :: 3.10
Classifier: Programming Language :: Python :: 3.11
Classifier: Programming Language :: Python :: 3.12
Classifier: Programming Language :: Python :: 3.13
Classifier: Programming Language :: Python :: 3.14
Requires-Dist: bitstring (>=4.2.1,<5.0.0)
Requires-Dist: brainstem (>=2.11.1,<3.0.0)
Requires-Dist: fastapi (>=0.128.0,<0.129.0)
Requires-Dist: matplotlib (>=3.10.8,<4.0.0)
Requires-Dist: pyocd (>=0.36.0,<0.37.0)
Requires-Dist: pyserial (>=3.5,<4.0)
Requires-Dist: pytest (>=7.2.1,<8.0.0)
Requires-Dist: pyvisa (>=1.13.0,<2.0.0)
